spectro_connect.py
spectro_connect-0.1.1.dist-info/LICENSE
spectro_connect-0.1.1.dist-info/METADATA
spectro_connect-0.1.1.dist-info/WHEEL
spectro_connect-0.1.1.dist-info/entry_points.txt
spectro_connect-0.1.1.dist-info/top_level.txt
spectro_connect-0.1.1.dist-info/RECORD
