Metadata-Version: 2.1
Name: spectro-connect
Version: 0.1.1
Summary: CLI tool to connect to devices via SpectroServer (DX Spectrum)
Home-page: https://github.com/johnrdowson/spectro_connect
Author: John Dowson
Author-email: john.dowson@sse.com
License: MIT
Platform: UNKNOWN
Classifier: Programming Language :: Python :: 3
Classifier: Programming Language :: Python :: 3.6
Classifier: Programming Language :: Python :: 3.7
Classifier: Programming Language :: Python :: 3.8
Classifier: License :: OSI Approved :: MIT License
Classifier: Operating System :: OS Independent
Requires-Python: >=3.6
Requires-Dist: requests
Requires-Dist: lxml
